steam_reviews/__init__.py
steam_reviews/review_loader.py
steam_reviews/reviews.py
test/__init__.py
test/test_reviews.py
steam_reviews-0.1.2.dist-info/LICENSE
steam_reviews-0.1.2.dist-info/METADATA
steam_reviews-0.1.2.dist-info/WHEEL
steam_reviews-0.1.2.dist-info/top_level.txt
steam_reviews-0.1.2.dist-info/RECORD
