Metadata-Version: 2.1
Name: steam-reviews
Version: 0.1.2
Summary: A package of getting game reviews from steam platform easily, for further text analytics projects.
Home-page: https://github.com/TommyXu97/SteamReviews
Author: Haotian Xu
Author-email: i@xht97.cn
License: UNKNOWN
Platform: UNKNOWN
Classifier: Programming Language :: Python :: 3
Classifier: License :: OSI Approved :: MIT License
Classifier: Operating System :: OS Independent
Requires-Python: >=3
Requires-Dist: requests
Requires-Dist: tqdm
